excel_mapper/__init__.py
excel_mapper/core.py
excel_mapper/version.py
excel_mapper-1.0.0.dist-info/licenses/LICENSE
excel_mapper-1.0.0.dist-info/METADATA
excel_mapper-1.0.0.dist-info/WHEEL
excel_mapper-1.0.0.dist-info/top_level.txt
excel_mapper-1.0.0.dist-info/RECORD
