Metadata-Version: 2.4
Name: excel-mapper
Version: 1.0.0
Summary: Map Excel columns to Python object attributes with dynamic access
Author-email: Payas Kale <payaskale99@gmail.com>
License: MIT
Project-URL: Homepage, https://github.com/spllat-00/excel-mapper
Project-URL: Repository, https://github.com/spllat-00/excel-mapper
Project-URL: Issues, https://github.com/spllat-00/excel-mapper/issues
Requires-Python: >=3.7
License-File: LICENSE
Requires-Dist: pandas>=1.0
Requires-Dist: openpyxl>=3.0
Dynamic: license-file
